notsteov/__init__.py
notsteov-0.1.11.dist-info/LICENSE.txt
notsteov-0.1.11.dist-info/METADATA
notsteov-0.1.11.dist-info/WHEEL
notsteov-0.1.11.dist-info/top_level.txt
notsteov-0.1.11.dist-info/RECORD
